[
    {"SourseFrom": "敏感视频","SenstiKind": "黄色敏感","Class":"高级","time": "1999-01-21 03:08:00"},
    {"SourseFrom": "敏感图片","SenstiKind": "政治敏感","Class":"高级","time": "1999-01-21 03:08:00"},
    {"SourseFrom": "敏感视频","SenstiKind": "政治敏感","Class":"高级","time": "1999-01-21 03:08:00"},
    {"SourseFrom": "敏感文字","SenstiKind": "政治敏感","Class":"高级","time": "1988-09-06 15:37:31"},
    {"SourseFrom": "敏感视频","SenstiKind": "黄色敏感","Class":"中级","time": "1999-01-21 03:08:00"},
    {"SourseFrom": "敏感视频","SenstiKind": "黄色敏感","Class":"高级","time": "1999-01-21 03:08:00"},
    {"SourseFrom": "敏感图片","SenstiKind": "黄色敏感","Class":"高级","time": "2014-11-07 00:42:00"},
    {"SourseFrom": "敏感视频","SenstiKind": "黄色敏感","Class":"中级","time": "1977-02-24 22:38:59"},
    {"SourseFrom": "敏感图片","SenstiKind": "黄色敏感","Class":"高级","time": "1988-09-06 15:37:31"},
    {"SourseFrom": "敏感视频","SenstiKind": "黄色敏感","Class":"中级","time": "1999-01-21 03:08:00"},
    {"SourseFrom": "敏感视频","SenstiKind": "黄色敏感","Class":"高级","time": "2014-11-07 00:42:00"},
    {"SourseFrom": "敏感图片","SenstiKind": "黄色敏感","Class":"中级","time": "1999-01-21 03:08:00"},
    {"SourseFrom": "敏感视频","SenstiKind": "黄色敏感","Class":"高级","time": "1999-01-21 03:08:00"},
    {"SourseFrom": "敏感视频","SenstiKind": "黄色敏感","Class":"高级","time": "1999-01-21 03:08:00"},
    {"SourseFrom": "敏感文字","SenstiKind": "黄色敏感","Class":"高级","time": "1999-01-21 03:08:00"},
    {"SourseFrom": "敏感视频","SenstiKind": "黄色敏感","Class":"低级","time": "1999-01-21 03:08:00"},
    {"SourseFrom": "敏感视频","SenstiKind": "暴力敏感","Class":"高级","time": "1999-01-21 03:08:00"},
    {"SourseFrom": "敏感文字","SenstiKind": "黄色敏感","Class":"高级","time": "1999-01-21 03:08:00"},
    {"SourseFrom": "敏感文字","SenstiKind": "暴力敏感","Class":"高级","time": "1999-01-21 03:08:00"},
    {"SourseFrom": "敏感图片","SenstiKind": "黄色敏感","Class":"高级","time": "1999-01-21 03:08:00"},
    {"SourseFrom": "敏感图片","SenstiKind": "黄色敏感","Class":"高级","time": "1999-01-21 03:08:00"},
    {"SourseFrom": "敏感视频","SenstiKind": "黄色敏感","Class":"低级","time": "1999-01-21 03:08:00"},
    {"SourseFrom": "敏感视频","SenstiKind": "暴力敏感","Class":"低级","time": "1999-01-21 03:08:00"},
    {"SourseFrom": "敏感视频","SenstiKind": "黄色敏感","Class":"高级","time": "1982-01-11 16:04:19"},
    {"SourseFrom": "敏感文字","SenstiKind": "暴力敏感","Class":"低级","time": "1999-01-21 03:08:00"},
    {"SourseFrom": "敏感文字","SenstiKind": "黄色敏感","Class":"低级","time": "1999-01-21 03:08:00"},
    {"SourseFrom": "敏感文字","SenstiKind": "暴力敏感","Class":"低级","time": "1999-01-21 03:08:00"},
    {"SourseFrom": "敏感文字","SenstiKind": "暴力敏感","Class":"低级","time": "1982-01-11 16:04:19"},
    {"SourseFrom": "敏感文字","SenstiKind": "黄色敏感","Class":"低级","time": "1999-01-21 03:08:00"},
    {"SourseFrom": "敏感视频","SenstiKind": "黄色敏感","Class":"高级","time": "1999-01-21 03:08:00"},
    {"SourseFrom": "敏感视频","SenstiKind": "暴力敏感","Class":"低级","time": "2001-02-14 08:06:56"},
    {"SourseFrom": "敏感视频","SenstiKind": "黄色敏感","Class":"高级","time": "1988-09-06 15:37:31"},
    {"SourseFrom": "敏感视频","SenstiKind": "黄色敏感","Class":"高级","time": "2014-11-07 00:42:00"},
    {"SourseFrom": "敏感图片","SenstiKind": "黄色敏感","Class":"中级","time": "1999-01-21 03:08:00"},
    {"SourseFrom": "敏感视频","SenstiKind": "黄色敏感","Class":"高级","time": "1999-01-21 03:08:00"},
    {"SourseFrom": "敏感视频","SenstiKind": "黄色敏感","Class":"高级","time": "1999-01-21 03:08:00"},
    {"SourseFrom": "敏感文字","SenstiKind": "黄色敏感","Class":"高级","time": "1999-01-21 03:08:00"},
    {"SourseFrom": "敏感视频","SenstiKind": "黄色敏感","Class":"低级","time": "1999-01-21 03:08:00"},
    {"SourseFrom": "敏感视频","SenstiKind": "暴力敏感","Class":"高级","time": "1999-01-21 03:08:00"},
    {"SourseFrom": "敏感文字","SenstiKind": "黄色敏感","Class":"高级","time": "1999-01-21 03:08:00"},
    {"SourseFrom": "敏感文字","SenstiKind": "暴力敏感","Class":"高级","time": "1999-01-21 03:08:00"},
    {"SourseFrom": "敏感图片","SenstiKind": "黄色敏感","Class":"高级","time": "1999-01-21 03:08:00"},
    {"SourseFrom": "敏感图片","SenstiKind": "黄色敏感","Class":"高级","time": "1999-01-21 03:08:00"},
    {"SourseFrom": "敏感视频","SenstiKind": "黄色敏感","Class":"低级","time": "1999-01-21 03:08:00"},
    {"SourseFrom": "敏感视频","SenstiKind": "暴力敏感","Class":"低级","time": "1999-01-21 03:08:00"},
    {"SourseFrom": "敏感视频","SenstiKind": "黄色敏感","Class":"高级","time": "1982-01-11 16:04:19"},
    {"SourseFrom": "敏感文字","SenstiKind": "暴力敏感","Class":"低级","time": "1999-01-21 03:08:00"},
    {"SourseFrom": "敏感文字","SenstiKind": "黄色敏感","Class":"低级","time": "1999-01-21 03:08:00"},
    {"SourseFrom": "敏感文字","SenstiKind": "暴力敏感","Class":"低级","time": "1999-01-21 03:08:00"},
    {"SourseFrom": "敏感文字","SenstiKind": "暴力敏感","Class":"低级","time": "1982-01-11 16:04:19"},
    {"SourseFrom": "敏感文字","SenstiKind": "黄色敏感","Class":"低级","time": "1999-01-21 03:08:00"},
    {"SourseFrom": "敏感视频","SenstiKind": "黄色敏感","Class":"高级","time": "1999-01-21 03:08:00"},
    {"SourseFrom": "敏感视频","SenstiKind": "暴力敏感","Class":"低级","time": "2001-02-14 08:06:56"},
    {"SourseFrom": "敏感视频","SenstiKind": "黄色敏感","Class":"高级","time": "1988-09-06 15:37:31"},
    {"SourseFrom": "敏感视频","SenstiKind": "黄色敏感","Class":"高级","time": "1999-01-21 03:08:00"},
    {"SourseFrom": "敏感文字","SenstiKind": "黄色敏感","Class":"高级","time": "1999-01-21 03:08:00"},
    {"SourseFrom": "敏感视频","SenstiKind": "黄色敏感","Class":"低级","time": "1999-01-21 03:08:00"},
    {"SourseFrom": "敏感视频","SenstiKind": "暴力敏感","Class":"高级","time": "1999-01-21 03:08:00"},
    {"SourseFrom": "敏感文字","SenstiKind": "黄色敏感","Class":"高级","time": "1999-01-21 03:08:00"},
    {"SourseFrom": "敏感文字","SenstiKind": "暴力敏感","Class":"高级","time": "1999-01-21 03:08:00"},
    {"SourseFrom": "敏感图片","SenstiKind": "黄色敏感","Class":"高级","time": "1999-01-21 03:08:00"},
    {"SourseFrom": "敏感图片","SenstiKind": "黄色敏感","Class":"高级","time": "1999-01-21 03:08:00"},
    {"SourseFrom": "敏感视频","SenstiKind": "黄色敏感","Class":"低级","time": "1999-01-21 03:08:00"},
    {"SourseFrom": "敏感视频","SenstiKind": "暴力敏感","Class":"低级","time": "1999-01-21 03:08:00"},
    {"SourseFrom": "敏感视频","SenstiKind": "黄色敏感","Class":"高级","time": "1982-01-11 16:04:19"},
    {"SourseFrom": "敏感文字","SenstiKind": "暴力敏感","Class":"低级","time": "1999-01-21 03:08:00"},
    {"SourseFrom": "敏感文字","SenstiKind": "黄色敏感","Class":"低级","time": "1999-01-21 03:08:00"},
    {"SourseFrom": "敏感文字","SenstiKind": "暴力敏感","Class":"低级","time": "1999-01-21 03:08:00"},
    {"SourseFrom": "敏感文字","SenstiKind": "暴力敏感","Class":"低级","time": "1982-01-11 16:04:19"},
    {"SourseFrom": "敏感文字","SenstiKind": "黄色敏感","Class":"低级","time": "1999-01-21 03:08:00"},
    {"SourseFrom": "敏感视频","SenstiKind": "黄色敏感","Class":"高级","time": "1999-01-21 03:08:00"},
    {"SourseFrom": "敏感视频","SenstiKind": "暴力敏感","Class":"低级","time": "2001-02-14 08:06:56"},
    {"SourseFrom": "敏感视频","SenstiKind": "黄色敏感","Class":"高级","time": "1988-09-06 15:37:31"},
    {"SourseFrom": "敏感视频","SenstiKind": "黄色敏感","Class":"高级","time": "2014-11-07 00:42:00"},
    {"SourseFrom": "敏感图片","SenstiKind": "黄色敏感","Class":"中级","time": "1999-01-21 03:08:00"},
    {"SourseFrom": "敏感视频","SenstiKind": "涉赌敏感","Class":"高级","time": "1999-01-21 03:08:00"},
    {"SourseFrom": "敏感视频","SenstiKind": "黄色敏感","Class":"高级","time": "1999-01-21 03:08:00"},
    {"SourseFrom": "敏感文字","SenstiKind": "黄色敏感","Class":"高级","time": "1999-01-21 03:08:00"},
    {"SourseFrom": "敏感视频","SenstiKind": "涉毒敏感","Class":"低级","time": "1999-01-21 03:08:00"},
    {"SourseFrom": "敏感视频","SenstiKind": "暴力敏感","Class":"高级","time": "1999-01-21 03:08:00"},
    {"SourseFrom": "敏感文字","SenstiKind": "黄色敏感","Class":"高级","time": "1999-01-21 03:08:00"},
    {"SourseFrom": "敏感文字","SenstiKind": "暴力敏感","Class":"高级","time": "1999-01-21 03:08:00"},
    {"SourseFrom": "敏感图片","SenstiKind": "黄色敏感","Class":"高级","time": "1999-01-21 03:08:00"},
    {"SourseFrom": "敏感图片","SenstiKind": "黄色敏感","Class":"高级","time": "1999-01-21 03:08:00"},
    {"SourseFrom": "敏感视频","SenstiKind": "黄色敏感","Class":"低级","time": "1999-01-21 03:08:00"},
    {"SourseFrom": "敏感视频","SenstiKind": "暴力敏感","Class":"低级","time": "1999-01-21 03:08:00"},
    {"SourseFrom": "敏感视频","SenstiKind": "黄色敏感","Class":"高级","time": "1982-01-11 16:04:19"},
    {"SourseFrom": "敏感文字","SenstiKind": "暴力敏感","Class":"低级","time": "1999-01-21 03:08:00"},
    {"SourseFrom": "敏感文字","SenstiKind": "黄色敏感","Class":"低级","time": "1999-01-21 03:08:00"},
    {"SourseFrom": "敏感文字","SenstiKind": "暴力敏感","Class":"低级","time": "1999-01-21 03:08:00"},
    {"SourseFrom": "敏感文字","SenstiKind": "暴力敏感","Class":"低级","time": "1982-01-11 16:04:19"},
    {"SourseFrom": "敏感文字","SenstiKind": "黄色敏感","Class":"低级","time": "1999-01-21 03:08:00"},
    {"SourseFrom": "敏感视频","SenstiKind": "黄色敏感","Class":"高级","time": "1999-01-21 03:08:00"},
    {"SourseFrom": "敏感视频","SenstiKind": "暴力敏感","Class":"低级","time": "2001-02-14 08:06:56"},
    {"SourseFrom": "敏感视频","SenstiKind": "黄色敏感","Class":"高级","time": "1988-09-06 15:37:31"},
    {"SourseFrom": "敏感视频","SenstiKind": "黄色敏感","Class":"高级","time": "1982-01-11 16:04:19"},
    {"SourseFrom": "敏感文字","SenstiKind": "暴力敏感","Class":"低级","time": "1999-01-21 03:08:00"},
    {"SourseFrom": "敏感文字","SenstiKind": "黄色敏感","Class":"低级","time": "1999-01-21 03:08:00"},
    {"SourseFrom": "敏感文字","SenstiKind": "暴力敏感","Class":"低级","time": "1999-01-21 03:08:00"},
    {"SourseFrom": "敏感文字","SenstiKind": "暴力敏感","Class":"低级","time": "1982-01-11 16:04:19"},
    {"SourseFrom": "敏感文字","SenstiKind": "黄色敏感","Class":"低级","time": "1999-01-21 03:08:00"},
    {"SourseFrom": "敏感视频","SenstiKind": "黄色敏感","Class":"高级","time": "1999-01-21 03:08:00"},
    {"SourseFrom": "敏感视频","SenstiKind": "暴力敏感","Class":"低级","time": "2001-02-14 08:06:56"},
    {"SourseFrom": "敏感视频","SenstiKind": "黄色敏感","Class":"高级","time": "1988-09-06 15:37:31"},
    {"SourseFrom": "敏感视频","SenstiKind": "黄色敏感","Class":"高级","time": "2014-11-07 00:42:00"},
    {"SourseFrom": "敏感图片","SenstiKind": "黄色敏感","Class":"中级","time": "1999-01-21 03:08:00"},
    {"SourseFrom": "敏感视频","SenstiKind": "黄色敏感","Class":"高级","time": "1999-01-21 03:08:00"},
    {"SourseFrom": "敏感视频","SenstiKind": "涉政敏感","Class":"高级","time": "1999-01-21 03:08:00"},
    {"SourseFrom": "敏感文字","SenstiKind": "黄色敏感","Class":"高级","time": "1999-01-21 03:08:00"},
    {"SourseFrom": "敏感视频","SenstiKind": "黄色敏感","Class":"低级","time": "1999-01-21 03:08:00"},
    {"SourseFrom": "敏感视频","SenstiKind": "暴力敏感","Class":"高级","time": "1999-01-21 03:08:00"},
    {"SourseFrom": "敏感文字","SenstiKind": "黄色敏感","Class":"高级","time": "1999-01-21 03:08:00"},
    {"SourseFrom": "敏感文字","SenstiKind": "暴力敏感","Class":"高级","time": "1999-01-21 03:08:00"},
    {"SourseFrom": "敏感图片","SenstiKind": "黄色敏感","Class":"高级","time": "1999-01-21 03:08:00"},
    {"SourseFrom": "敏感图片","SenstiKind": "黄色敏感","Class":"高级","time": "1999-01-21 03:08:00"},
    {"SourseFrom": "敏感视频","SenstiKind": "黄色敏感","Class":"低级","time": "1999-01-21 03:08:00"},
    {"SourseFrom": "敏感视频","SenstiKind": "暴力敏感","Class":"低级","time": "1999-01-21 03:08:00"},
    {"SourseFrom": "敏感视频","SenstiKind": "黄色敏感","Class":"高级","time": "1982-01-11 16:04:19"},
    {"SourseFrom": "敏感文字","SenstiKind": "暴力敏感","Class":"低级","time": "1999-01-21 03:08:00"},
    {"SourseFrom": "敏感文字","SenstiKind": "黄色敏感","Class":"低级","time": "1999-01-21 03:08:00"},
    {"SourseFrom": "敏感文字","SenstiKind": "暴力敏感","Class":"低级","time": "1999-01-21 03:08:00"},
    {"SourseFrom": "敏感文字","SenstiKind": "暴力敏感","Class":"低级","time": "1982-01-11 16:04:19"},
    {"SourseFrom": "敏感文字","SenstiKind": "黄色敏感","Class":"低级","time": "1999-01-21 03:08:00"},
    {"SourseFrom": "敏感视频","SenstiKind": "黄色敏感","Class":"高级","time": "1999-01-21 03:08:00"},
    {"SourseFrom": "敏感视频","SenstiKind": "暴力敏感","Class":"低级","time": "2001-02-14 08:06:56"},
    {"SourseFrom": "敏感视频","SenstiKind": "黄色敏感","Class":"高级","time": "1988-09-06 15:37:31"}
]